orewaagentmcp/__init__.py
orewaagentmcp/main.py
orewaagentmcp/utility.py
orewaagentmcp-0.1.0.dist-info/METADATA
orewaagentmcp-0.1.0.dist-info/WHEEL
orewaagentmcp-0.1.0.dist-info/entry_points.txt
orewaagentmcp-0.1.0.dist-info/top_level.txt
orewaagentmcp-0.1.0.dist-info/RECORD
