Metadata-Version: 2.4
Name: orewaagentmcp
Version: 0.1.0
Summary: OMEGAPy's General Purpose MCP Server
Requires-Python: >=3.13
Requires-Dist: ddgs>=9.6.0
Requires-Dist: fastmcp>=2.12.4
Requires-Dist: gitpython>=3.1.45
Requires-Dist: google-genai>=1.41.0
Requires-Dist: python-dotenv>=1.1.1
Requires-Dist: trafilatura>=1.6.1
